<?xml version="1.0"?>
<opencv_storage>
<stage7>
  <maxWeakCount>4</maxWeakCount>
  <stageThreshold>-1.1581282615661621e+00</stageThreshold>
  <weakClassifiers>
    <_>
      <internalNodes>
        0 -1 159638 1.2860945389547851e-05</internalNodes>
      <leafValues>
        -1.9425287842750549e-01 -8.5259258747100830e-01</leafValues></_>
    <_>
      <internalNodes>
        0 -1 162108 -1.2946425158588681e-05</internalNodes>
      <leafValues>
        -8.4692955017089844e-01 1.2919297814369202e-01</leafValues></_>
    <_>
      <internalNodes>
        0 -1 6978 -1.6100409626960754e-01</internalNodes>
      <leafValues>
        5.6893575191497803e-01 -4.1547000408172607e-01</leafValues></_>
    <_>
      <internalNodes>
        0 -1 68202 -1.6555827111005783e-02</internalNodes>
      <leafValues>
        -6.7759829759597778e-01 3.0643218755722046e-01</leafValues></_></weakClassifiers></stage7>
</opencv_storage>
